arcane/pubsub/__init__.py
arcane/pubsub/client.py
arcane/pubsub/gcp_component_retrieve_info_lib.py
arcane/pubsub/utils.py
arcane_pubsub-1.4.0.dist-info/METADATA
arcane_pubsub-1.4.0.dist-info/WHEEL
arcane_pubsub-1.4.0.dist-info/RECORD
