Metadata-Version: 2.4
Name: arcane-pubsub
Version: 1.4.0
Summary: Override pubsub client
Author: Arcane
Author-email: product@wearcane.com
Requires-Python: >=3.6,<4.0
Classifier: Programming Language :: Python :: 3
Classifier: Programming Language :: Python :: 3.6
Classifier: Programming Language :: Python :: 3.7
Classifier: Programming Language :: Python :: 3.8
Classifier: Programming Language :: Python :: 3.9
Classifier: Programming Language :: Python :: 3.10
Classifier: Programming Language :: Python :: 3.11
Classifier: Programming Language :: Python :: 3.12
Classifier: Programming Language :: Python :: 3.13
Classifier: Programming Language :: Python :: 3.14
Requires-Dist: arcane-firebase (>=0.2.0,<0.3.0)
Requires-Dist: avro (>=1.11.2,<2.0.0)
Requires-Dist: google-cloud-pubsub (>=2.11.0,<3.0.0)
Requires-Dist: typing-extensions (>=3.7)
